selectel_dns_api/__init__.py
selectel_dns_api/api_client.py
selectel_dns_api/configuration.py
selectel_dns_api/rest.py
selectel_dns_api/apis/__init__.py
selectel_dns_api/apis/domains_api.py
selectel_dns_api/apis/ptr_api.py
selectel_dns_api/apis/records_api.py
selectel_dns_api/apis/tags_api.py
selectel_dns_api/models/__init__.py
selectel_dns_api/models/api_response.py
selectel_dns_api/models/batch_update_model.py
selectel_dns_api/models/domain.py
selectel_dns_api/models/new_domain.py
selectel_dns_api/models/new_or_updated_ptr_record.py
selectel_dns_api/models/new_or_updated_record.py
selectel_dns_api/models/new_or_updated_tag.py
selectel_dns_api/models/ptr_record.py
selectel_dns_api/models/record.py
selectel_dns_api/models/tag.py
selectel_dns_api/models/updated_domain.py
selectel_dns_api-1.0.2.dist-info/DESCRIPTION.rst
selectel_dns_api-1.0.2.dist-info/METADATA
selectel_dns_api-1.0.2.dist-info/RECORD
selectel_dns_api-1.0.2.dist-info/WHEEL
selectel_dns_api-1.0.2.dist-info/metadata.json
selectel_dns_api-1.0.2.dist-info/top_level.txt
test/__init__.py
test/test_api_response.py
test/test_batch_update_model.py
test/test_domain.py
test/test_domains_api.py
test/test_new_domain.py
test/test_new_or_updated_ptr_record.py
test/test_new_or_updated_record.py
test/test_new_or_updated_tag.py
test/test_ptr_api.py
test/test_ptr_record.py
test/test_record.py
test/test_records_api.py
test/test_tag.py
test/test_tags_api.py
test/test_updated_domain.py
