Metadata-Version: 2.0
Name: selectel-dns-api
Version: 1.0.2
Summary: Selectel DNS API
Home-page: https://github.com/viasite/selectel-dns-api
Author: UNKNOWN
Author-email: info@mdsina.ru
License: UNKNOWN
Keywords: Swagger,Selectel DNS API
Platform: UNKNOWN
Requires-Dist: urllib3 (>=1.15)
Requires-Dist: six (>=1.10)
Requires-Dist: certifi
Requires-Dist: python-dateutil
